{
  "type": "minecraft:crafting_shaped",
  "pattern": [
    " R ",
    "SCS",
    "SRS"  ],
  "key": {
    "S": [
      {
        "type": "forge:ore_dict",
        "ore": "ingotDarkSteel"
      }
    ],
    "C": [
      {
        "item": "enderio:item_capacitor_vivid",
        "data": 0
      }
    ],
    "R": [
      {
        "type": "forge:ore_dict",
        "ore": "ingotVividAlloy"
      }
    ]
  },
  "result": {
    "item": "superiorshields:endergy_ds_shield_vivid_alloy",
    "data": 0
  }
}